{"id":129995,"xmlId":"com.jetbrains.php","name":"PHP","description":"PHP 5.3-8.1 editing and debugging, PHPUnit, Smarty, Twig and various frameworks support","organization":"JetBrains s.r.o.","tags":["Programming Language"],"vendor":"JetBrains","version":"212.4746.100","dependencies":["com.intellij.modules.xml","com.intellij.modules.ultimate","com.intellij.modules.php-capable"],"optionalDependencies":["com.intellij.diagram","com.intellij.modules.coverage","com.jetbrains.plugins.webDeployment","org.intellij.intelliLang","com.intellij.plugins.html.instantEditing","com.jetbrains.restClient","com.intellij.copyright","com.intellij.modules.duplicatesDetector","com.jetbrains.performancePlugin","intellij.indexing.shared","intellij.indexing.shared.core"],"since":"212.4746","until":"212.*","size":14670925}